{
  "version": "0.4.29",
  "flags": {},
  "shapes": [
    {
      "label": "b",
      "text": "",
      "points": [
        [
          167.0,
          81.0
        ],
        [
          164.0,
          90.0
        ],
        [
          602.0,
          923.0
        ],
        [
          608.0,
          924.0
        ],
        [
          623.0,
          915.0
        ],
        [
          658.0,
          881.0
        ],
        [
          891.0,
          758.0
        ],
        [
          912.0,
          762.0
        ],
        [
          927.0,
          753.0
        ],
        [
          905.0,
          705.0
        ],
        [
          513.0,
          0.0
        ],
        [
          438.0,
          2.0
        ],
        [
          254.0,
          106.0
        ],
        [
          238.0,
          106.0
        ],
        [
          187.0,
          79.0
        ]
      ],
      "group_id": null,
      "shape_type": "polygon",
      "flags": {}
    }
  ],
  "imagePath": "_rgb_000008.png",
  "imageData": null,
  "imageHeight": 1024,
  "imageWidth": 1280
}